<?xml version="1.0" encoding="UTF-8" ?>
	<Module>
	<ModulePrefs title="API Demo">
	    <Require feature="opensocial-templates"/>
	    <Require feature="opensocial-data"/>
	    <Require feature="views"/>
	    <Require feature="dynamic-height"/>
	    <Require feature="osapi"/>
	  </ModulePrefs>
        <Content type="html" view="home">
	  <![CDATA[
		<!--<script src='http://ajax.googleapis.com/ajax/libs/jquery/1.9.1/jquery.min.js' type='text/javascript'></script>-->
	      <script src='../rs/js/jquery.min.js' type='text/javascript'></script>
	    <script type="text/javascript" language="javascript">
			/* Global Varaibles Start */ 
			   var sabaCertificate ;
			   var employeeID ;
			   var userName ;
			   var urlAPIRole ;   
			   var varRoleID;
			   var refreshInterval=1;
			   var  errorAPIRoleAssigmnet = "Insufficient Privileges: You do not have Can add required/optional role for self privilege on Person, Internal";
			   var varRoleDetailPDFlocation ;//= "https://raw.githubusercontent.com/poc-org/initiative/itg/doc/";
		   /* Global Varaibles END */ 
                  alert("shakeel");
		viewData = gadgets.views.getParams();   
alert("shakeel111");
		   // sabaCertificate =  viewData.sabaContext.apiCertificate;
		    userName = $.trim(viewData.sabaContext.userName);			
		    employeeID = $.trim(viewData.sabaContext.userId) ;			
		    urlAPIRole =  $.trim(decodeURIComponent(viewData.sabaParams.saba_api_url))+'/v1/' ;
                  //alert(userName +" -- "+employeeID);
	   // gadgets.util.registerOnLoadHandler(init);
	   
	    </script>
	    <!-- Header of the Page Start -->
	    <!-- Header of the Page END-->
	    <!-- Search Box Start-->
	<div  style="height:600px">
	    <div id="divRoleForm">
		<div>
		    <center>
		       <table border="10" cellpadding="10" cellspacing="10" >
			    <tr>
				<td align="center"  style="font-weight:bold;">
				    Profile Links
				</td>
			    </tr>
			    <tr>                            
				    <td align="center" >
					 My Profile 
				    </td>
			    </tr>
			    <tr>
				<td>
				    <table align="center">
					<tr>
					    <td align="center">
						My Plan
					    </td>
					</tr>
				    </table>
				</td>
			    </tr>
			</table>
		    </center>
		</div>
	    </div>
	    <!-- Search Box END-->
	
	    </script>
	  ]]>
	  </Content>
	</Module>
